{
"nom_fitxer" : "res://Dades Json/Població-10_Inputs-[0,1,2]_Mutacions-[0]_0.json",
"data_mostra" : "19/7/2024 13:7:50",
"configuracio" :
{
"població" : 10,
"inputs" : [0, 1, 2],
"mutacions" : [0],
"partides_totals" : 20,
"generacions totals" : 125,
"Puntuació màxima" : 150
},
"partides" : [
{
"num_partida" :0,
"generacions" :
[
{
"num_generacio" : 1,
"fitness" : 116.45
},
{
"num_generacio" : 2,
"fitness" : 25.5
},
{
"num_generacio" : 3,
"fitness" : 25.5
},
{
"num_generacio" : 4,
"fitness" : 25.5
},
{
"num_generacio" : 5,
"fitness" : 166.55
},
{
"num_generacio" : 6,
"fitness" : 157.9
},
{
"num_generacio" : 7,
"fitness" : 162.5
},
{
"num_generacio" : 8,
"fitness" : 3347.15000000001
},
{
"num_generacio" : 9,
"fitness" : 1345.3
},
{
"num_generacio" : 10,
"fitness" : 2419.9
},
{
"num_generacio" : 11,
"fitness" : 3486.15000000001
},
{
"num_generacio" : 12,
"fitness" : 214.5
},
{
"num_generacio" : 13,
"fitness" : 269.35
},
{
"num_generacio" : 14,
"fitness" : 7919.85000000003
},
{
"num_generacio" : 15,
"fitness" : 4580.25000000002
},
{
"num_generacio" : 16,
"fitness" : 17844.4999999998
},
{
"num_generacio" : 17,
"fitness" : 152233.500000001
},
{
"num_generacio" : 18,
"fitness" : 163269.399999997
},
{
"num_generacio" : 19,
"fitness" : 164178.199999997
},
{
"num_generacio" : 20,
"fitness" : 153304.85
},
{
"num_generacio" : 21,
"fitness" : 91487.4000000046
},
{
"num_generacio" : 22,
"fitness" : 50385.5000000011
},
{
"num_generacio" : 23,
"fitness" : 131552.150000008
},
{
"num_generacio" : 24,
"fitness" : 164113.949999997
},
{
"num_generacio" : 25,
"fitness" : 162837.949999997
},
{
"num_generacio" : 26,
"fitness" : 164179.699999997
}
],
"màxim_fitness" :164179.699999997,
"millor_ocell" :
{
"neurones_input" : 3,
"neurones_amagades" :0,
"neuornes_output" :1,
"conexions" :[
{
"desde" :0,
"fins" :3,
"importancia" :0.51413416862488},
{
"desde" :1,
"fins" :3,
"importancia" :-0.54924666881561},
{
"desde" :2,
"fins" :3,
"importancia" :-0.00021290779114}
]
}
},
{
"num_partida" :1,
"generacions" :
[
{
"num_generacio" : 1,
"fitness" : 25.5
},
{
"num_generacio" : 2,
"fitness" : 25.5
},
{
"num_generacio" : 3,
"fitness" : 126.65
},
{
"num_generacio" : 4,
"fitness" : 93.1999999999999
},
{
"num_generacio" : 5,
"fitness" : 1202.9
},
{
"num_generacio" : 6,
"fitness" : 3398.25000000001
},
{
"num_generacio" : 7,
"fitness" : 189.75
},
{
"num_generacio" : 8,
"fitness" : 16295.9999999999
},
{
"num_generacio" : 9,
"fitness" : 6590.65000000003
},
{
"num_generacio" : 10,
"fitness" : 63857.6000000022
},
{
"num_generacio" : 11,
"fitness" : 14226.2499999999
},
{
"num_generacio" : 12,
"fitness" : 22655.8999999997
},
{
"num_generacio" : 13,
"fitness" : 4439.90000000002
},
{
"num_generacio" : 14,
"fitness" : 6634.35000000003
},
{
"num_generacio" : 15,
"fitness" : 5447.50000000002
},
{
"num_generacio" : 16,
"fitness" : 2395.95
},
{
"num_generacio" : 17,
"fitness" : 218.3
},
{
"num_generacio" : 18,
"fitness" : 164578.599999997
},
{
"num_generacio" : 19,
"fitness" : 164562.649999997
},
{
"num_generacio" : 20,
"fitness" : 164428.699999997
}
],
"màxim_fitness" :164578.599999997,
"millor_ocell" :
{
"neurones_input" : 3,
"neurones_amagades" :0,
"neuornes_output" :1,
"conexions" : [
{
"desde" :0,
"fins" :3,
"importancia" :0.54126620292664},
{
"desde" :1,
"fins" :3,
"importancia" :-0.50191617012024},
{
"desde" :2,
"fins" :3,
"importancia" :-0.15151506662369}
]
}
},
{
"num_partida" :2,
"generacions" :
[
{
"num_generacio" : 1,
"fitness" : 121.75
},
{
"num_generacio" : 2,
"fitness" : 145.25
},
{
"num_generacio" : 3,
"fitness" : 122.25
},
{
"num_generacio" : 4,
"fitness" : 181.75
},
{
"num_generacio" : 5,
"fitness" : 135.5
},
{
"num_generacio" : 6,
"fitness" : 126.5
},
{
"num_generacio" : 7,
"fitness" : 216.5
},
{
"num_generacio" : 8,
"fitness" : 214.5
},
{
"num_generacio" : 9,
"fitness" : 211
},
{
"num_generacio" : 10,
"fitness" : 149.5
},
{
"num_generacio" : 11,
"fitness" : 152
},
{
"num_generacio" : 12,
"fitness" : 144
},
{
"num_generacio" : 13,
"fitness" : 175.75
},
{
"num_generacio" : 14,
"fitness" : 135
},
{
"num_generacio" : 15,
"fitness" : 135
},
{
"num_generacio" : 16,
"fitness" : 144.5
},
{
"num_generacio" : 17,
"fitness" : 138.25
},
{
"num_generacio" : 18,
"fitness" : 227.5
},
{
"num_generacio" : 19,
"fitness" : 232.5
},
{
"num_generacio" : 20,
"fitness" : 134.75
},
{
"num_generacio" : 21,
"fitness" : 138.5
},
{
"num_generacio" : 22,
"fitness" : 154
},
{
"num_generacio" : 23,
"fitness" : 173.25
},
{
"num_generacio" : 24,
"fitness" : 151.5
},
{
"num_generacio" : 25,
"fitness" : 154
},
{
"num_generacio" : 26,
"fitness" : 211.25
},
{
"num_generacio" : 27,
"fitness" : 149.5
},
{
"num_generacio" : 28,
"fitness" : 210.5
},
{
"num_generacio" : 29,
"fitness" : 178.75
},
{
"num_generacio" : 30,
"fitness" : 135.25
},
{
"num_generacio" : 31,
"fitness" : 136
},
{
"num_generacio" : 32,
"fitness" : 190
},
{
"num_generacio" : 33,
"fitness" : 214
},
{
"num_generacio" : 34,
"fitness" : 232.850000000001
},
{
"num_generacio" : 35,
"fitness" : 201.25
},
{
"num_generacio" : 36,
"fitness" : 188
},
{
"num_generacio" : 37,
"fitness" : 219.75
},
{
"num_generacio" : 38,
"fitness" : 211.75
},
{
"num_generacio" : 39,
"fitness" : 232
},
{
"num_generacio" : 40,
"fitness" : 187.75
},
{
"num_generacio" : 41,
"fitness" : 1149.15
},
{
"num_generacio" : 42,
"fitness" : 208.9
},
{
"num_generacio" : 43,
"fitness" : 164.3
},
{
"num_generacio" : 44,
"fitness" : 203.05
},
{
"num_generacio" : 45,
"fitness" : 13229.0499999999
},
{
"num_generacio" : 46,
"fitness" : 72153.800000003
},
{
"num_generacio" : 47,
"fitness" : 11120.2
},
{
"num_generacio" : 48,
"fitness" : 63323.8000000022
},
{
"num_generacio" : 49,
"fitness" : 163688.949999997
},
{
"num_generacio" : 50,
"fitness" : 86.6999999999998
},
{
"num_generacio" : 51,
"fitness" : 58458.1500000018
},
{
"num_generacio" : 52,
"fitness" : 164078.649999997
},
{
"num_generacio" : 53,
"fitness" : 163851.949999997
},
{
"num_generacio" : 54,
"fitness" : 163909.699999997
}
],
"màxim_fitness" :164078.649999997,
"millor_ocell" :
{
"neurones_input" : 3,
"neurones_amagades" :0,
"neuornes_output" :1,
"conexions" : [
{
"desde" :0,
"fins" :3,
"importancia" :0.86289596557617},
{
"desde" :1,
"fins" :3,
"importancia" :-0.89268916845322},
{
"desde" :2,
"fins" :3,
"importancia" :-0.0125390291214}
]
}
},
{
"num_partida" :3,
"generacions" :
[
{
"num_generacio" : 1,
"fitness" : 25.5
},
{
"num_generacio" : 2,
"fitness" : 25.5
},
{
"num_generacio" : 3,
"fitness" : 96.4999999999998
},
{
"num_generacio" : 4,
"fitness" : 174.5
},
{
"num_generacio" : 5,
"fitness" : 2327.05
},
{
"num_generacio" : 6,
"fitness" : 210.65
},
{
"num_generacio" : 7,
"fitness" : 205.2
},
{
"num_generacio" : 8,
"fitness" : 175
},
{
"num_generacio" : 9,
"fitness" : 1228.15
},
{
"num_generacio" : 10,
"fitness" : 186.5
},
{
"num_generacio" : 11,
"fitness" : 164317.099999997
},
{
"num_generacio" : 12,
"fitness" : 164226.449999997
},
{
"num_generacio" : 13,
"fitness" : 164322.899999997
}
],
"màxim_fitness" :164322.899999997,
"millor_ocell" :
{
"neurones_input" : 3,
"neurones_amagades" :0,
"neuornes_output" :1,
"conexions" : [
{
"desde" :0,
"fins" :3,
"importancia" :0.65540075302124},
{
"desde" :1,
"fins" :3,
"importancia" :-0.60112887620926},
{
"desde" :2,
"fins" :3,
"importancia" :-0.19541257619858}
]
}
},
{
"num_partida" :4,
"generacions" :
[
{
"num_generacio" : 1,
"fitness" : 25.5
},
{
"num_generacio" : 2,
"fitness" : 34.4
},
{
"num_generacio" : 3,
"fitness" : 125
},
{
"num_generacio" : 4,
"fitness" : 126.75
},
{
"num_generacio" : 5,
"fitness" : 115
},
{
"num_generacio" : 6,
"fitness" : 159.25
},
{
"num_generacio" : 7,
"fitness" : 201
},
{
"num_generacio" : 8,
"fitness" : 204.5
},
{
"num_generacio" : 9,
"fitness" : 196.75
},
{
"num_generacio" : 10,
"fitness" : 237.5
},
{
"num_generacio" : 11,
"fitness" : 237
},
{
"num_generacio" : 12,
"fitness" : 143.5
},
{
"num_generacio" : 13,
"fitness" : 243.75
},
{
"num_generacio" : 14,
"fitness" : 148.5
},
{
"num_generacio" : 15,
"fitness" : 2303.05
},
{
"num_generacio" : 16,
"fitness" : 2319.3
},
{
"num_generacio" : 17,
"fitness" : 15429.6499999999
},
{
"num_generacio" : 18,
"fitness" : 4531.20000000002
},
{
"num_generacio" : 19,
"fitness" : 156.55
},
{
"num_generacio" : 20,
"fitness" : 2300.95
},
{
"num_generacio" : 21,
"fitness" : 1257.2
},
{
"num_generacio" : 22,
"fitness" : 2307.45
},
{
"num_generacio" : 23,
"fitness" : 1209.35
},
{
"num_generacio" : 24,
"fitness" : 3398.25000000001
},
{
"num_generacio" : 25,
"fitness" : 139.25
},
{
"num_generacio" : 26,
"fitness" : 3382.80000000001
},
{
"num_generacio" : 27,
"fitness" : 2308.4
},
{
"num_generacio" : 28,
"fitness" : 1208.85
},
{
"num_generacio" : 29,
"fitness" : 5597.65000000002
},
{
"num_generacio" : 30,
"fitness" : 1179.25
},
{
"num_generacio" : 31,
"fitness" : 3399.10000000001
},
{
"num_generacio" : 32,
"fitness" : 1168.7
},
{
"num_generacio" : 33,
"fitness" : 167.1
},
{
"num_generacio" : 34,
"fitness" : 1212.75
},
{
"num_generacio" : 35,
"fitness" : 3388.75000000001
},
{
"num_generacio" : 36,
"fitness" : 4446.70000000002
},
{
"num_generacio" : 37,
"fitness" : 4449.50000000002
},
{
"num_generacio" : 38,
"fitness" : 5599.60000000002
},
{
"num_generacio" : 39,
"fitness" : 3404.70000000001
},
{
"num_generacio" : 40,
"fitness" : 7733.95000000003
},
{
"num_generacio" : 41,
"fitness" : 8848.40000000001
},
{
"num_generacio" : 42,
"fitness" : 192.7
},
{
"num_generacio" : 43,
"fitness" : 199.7
},
{
"num_generacio" : 44,
"fitness" : 62756.7000000021
},
{
"num_generacio" : 45,
"fitness" : 26401.1999999996
},
{
"num_generacio" : 46,
"fitness" : 130974.750000008
},
{
"num_generacio" : 47,
"fitness" : 21010.6499999998
},
{
"num_generacio" : 48,
"fitness" : 164988.449999997
},
{
"num_generacio" : 49,
"fitness" : 23273.4499999997
},
{
"num_generacio" : 50,
"fitness" : 165269.699999996
},
{
"num_generacio" : 51,
"fitness" : 79216.9500000036
},
{
"num_generacio" : 52,
"fitness" : 66386.4000000025
},
{
"num_generacio" : 53,
"fitness" : 162909.199999997
},
{
"num_generacio" : 54,
"fitness" : 163038.099999997
},
{
"num_generacio" : 55,
"fitness" : 162803.649999997
}
],
"màxim_fitness" :165269.699999996,
"millor_ocell" :
{
"neurones_input" : 3,
"neurones_amagades" :0,
"neuornes_output" :1,
"conexions" : [
{
"desde" :0,
"fins" :3,
"importancia" :0.3802741765976},
{
"desde" :1,
"fins" :3,
"importancia" :-0.37838560342789},
{
"desde" :2,
"fins" :3,
"importancia" :-0.07273668050766}
]
}
},
{
"num_partida" :5,
"generacions" :
[
{
"num_generacio" : 1,
"fitness" : 53.9999999999999
},
{
"num_generacio" : 2,
"fitness" : 63.7499999999999
},
{
"num_generacio" : 3,
"fitness" : 65.9999999999999
},
{
"num_generacio" : 4,
"fitness" : 92.2499999999999
},
{
"num_generacio" : 5,
"fitness" : 58.4999999999999
},
{
"num_generacio" : 6,
"fitness" : 175.5
},
{
"num_generacio" : 7,
"fitness" : 112.75
},
{
"num_generacio" : 8,
"fitness" : 179.5
},
{
"num_generacio" : 9,
"fitness" : 138.75
},
{
"num_generacio" : 10,
"fitness" : 128
},
{
"num_generacio" : 11,
"fitness" : 124
},
{
"num_generacio" : 12,
"fitness" : 123.5
},
{
"num_generacio" : 13,
"fitness" : 144.25
},
{
"num_generacio" : 14,
"fitness" : 123.25
},
{
"num_generacio" : 15,
"fitness" : 180.25
},
{
"num_generacio" : 16,
"fitness" : 123.75
},
{
"num_generacio" : 17,
"fitness" : 180.25
},
{
"num_generacio" : 18,
"fitness" : 186
},
{
"num_generacio" : 19,
"fitness" : 150
},
{
"num_generacio" : 20,
"fitness" : 188.5
},
{
"num_generacio" : 21,
"fitness" : 164.5
},
{
"num_generacio" : 22,
"fitness" : 132.25
},
{
"num_generacio" : 23,
"fitness" : 145.25
},
{
"num_generacio" : 24,
"fitness" : 185
},
{
"num_generacio" : 25,
"fitness" : 151.5
},
{
"num_generacio" : 26,
"fitness" : 170
},
{
"num_generacio" : 27,
"fitness" : 150.75
},
{
"num_generacio" : 28,
"fitness" : 183
},
{
"num_generacio" : 29,
"fitness" : 150.75
},
{
"num_generacio" : 30,
"fitness" : 166.5
},
{
"num_generacio" : 31,
"fitness" : 131.75
},
{
"num_generacio" : 32,
"fitness" : 189.3
},
{
"num_generacio" : 33,
"fitness" : 183.25
},
{
"num_generacio" : 34,
"fitness" : 154.75
},
{
"num_generacio" : 35,
"fitness" : 148
},
{
"num_generacio" : 36,
"fitness" : 180.25
},
{
"num_generacio" : 37,
"fitness" : 187.5
},
{
"num_generacio" : 38,
"fitness" : 133.25
},
{
"num_generacio" : 39,
"fitness" : 183.5
},
{
"num_generacio" : 40,
"fitness" : 180
},
{
"num_generacio" : 41,
"fitness" : 132
},
{
"num_generacio" : 42,
"fitness" : 188.3
},
{
"num_generacio" : 43,
"fitness" : 189
},
{
"num_generacio" : 44,
"fitness" : 131
},
{
"num_generacio" : 45,
"fitness" : 169.75
},
{
"num_generacio" : 46,
"fitness" : 133.25
},
{
"num_generacio" : 47,
"fitness" : 135.5
},
{
"num_generacio" : 48,
"fitness" : 148.5
},
{
"num_generacio" : 49,
"fitness" : 135.5
},
{
"num_generacio" : 50,
"fitness" : 186.5
},
{
"num_generacio" : 51,
"fitness" : 138.25
},
{
"num_generacio" : 52,
"fitness" : 131.75
},
{
"num_generacio" : 53,
"fitness" : 131
},
{
"num_generacio" : 54,
"fitness" : 133
},
{
"num_generacio" : 55,
"fitness" : 160.25
},
{
"num_generacio" : 56,
"fitness" : 151
},
{
"num_generacio" : 57,
"fitness" : 189.5
},
{
"num_generacio" : 58,
"fitness" : 175.25
},
{
"num_generacio" : 59,
"fitness" : 188.25
},
{
"num_generacio" : 60,
"fitness" : 192.75
},
{
"num_generacio" : 61,
"fitness" : 170
},
{
"num_generacio" : 62,
"fitness" : 156.75
},
{
"num_generacio" : 63,
"fitness" : 151.25
},
{
"num_generacio" : 64,
"fitness" : 131.5
},
{
"num_generacio" : 65,
"fitness" : 135
},
{
"num_generacio" : 66,
"fitness" : 166.5
},
{
"num_generacio" : 67,
"fitness" : 137.5
},
{
"num_generacio" : 68,
"fitness" : 180.5
},
{
"num_generacio" : 69,
"fitness" : 150.25
},
{
"num_generacio" : 70,
"fitness" : 188.5
},
{
"num_generacio" : 71,
"fitness" : 183
},
{
"num_generacio" : 72,
"fitness" : 151.25
},
{
"num_generacio" : 73,
"fitness" : 182
},
{
"num_generacio" : 74,
"fitness" : 188.25
},
{
"num_generacio" : 75,
"fitness" : 137.5
},
{
"num_generacio" : 76,
"fitness" : 145.25
},
{
"num_generacio" : 77,
"fitness" : 187.25
},
{
"num_generacio" : 78,
"fitness" : 135.25
},
{
"num_generacio" : 79,
"fitness" : 140.5
},
{
"num_generacio" : 80,
"fitness" : 177
},
{
"num_generacio" : 81,
"fitness" : 132.25
},
{
"num_generacio" : 82,
"fitness" : 137.75
},
{
"num_generacio" : 83,
"fitness" : 161.75
},
{
"num_generacio" : 84,
"fitness" : 131.5
},
{
"num_generacio" : 85,
"fitness" : 188
},
{
"num_generacio" : 86,
"fitness" : 153
},
{
"num_generacio" : 87,
"fitness" : 157
},
{
"num_generacio" : 88,
"fitness" : 133
},
{
"num_generacio" : 89,
"fitness" : 154.75
},
{
"num_generacio" : 90,
"fitness" : 131.5
},
{
"num_generacio" : 91,
"fitness" : 132
},
{
"num_generacio" : 92,
"fitness" : 152.5
},
{
"num_generacio" : 93,
"fitness" : 190
},
{
"num_generacio" : 94,
"fitness" : 166.5
},
{
"num_generacio" : 95,
"fitness" : 131.5
},
{
"num_generacio" : 96,
"fitness" : 177.75
},
{
"num_generacio" : 97,
"fitness" : 145
},
{
"num_generacio" : 98,
"fitness" : 131.25
},
{
"num_generacio" : 99,
"fitness" : 150
},
{
"num_generacio" : 100,
"fitness" : 170
},
{
"num_generacio" : 101,
"fitness" : 140.25
},
{
"num_generacio" : 102,
"fitness" : 162
},
{
"num_generacio" : 103,
"fitness" : 170
},
{
"num_generacio" : 104,
"fitness" : 150.25
},
{
"num_generacio" : 105,
"fitness" : 188.5
},
{
"num_generacio" : 106,
"fitness" : 160.25
},
{
"num_generacio" : 107,
"fitness" : 143
},
{
"num_generacio" : 108,
"fitness" : 133.25
},
{
"num_generacio" : 109,
"fitness" : 160.25
},
{
"num_generacio" : 110,
"fitness" : 186.25
},
{
"num_generacio" : 111,
"fitness" : 148.5
},
{
"num_generacio" : 112,
"fitness" : 159.25
},
{
"num_generacio" : 113,
"fitness" : 186
},
{
"num_generacio" : 114,
"fitness" : 135.75
},
{
"num_generacio" : 115,
"fitness" : 182.5
},
{
"num_generacio" : 116,
"fitness" : 181.25
},
{
"num_generacio" : 117,
"fitness" : 166.5
},
{
"num_generacio" : 118,
"fitness" : 140.25
},
{
"num_generacio" : 119,
"fitness" : 188.5
},
{
"num_generacio" : 120,
"fitness" : 175.25
},
{
"num_generacio" : 121,
"fitness" : 132
},
{
"num_generacio" : 122,
"fitness" : 131.75
},
{
"num_generacio" : 123,
"fitness" : 151
},
{
"num_generacio" : 124,
"fitness" : 132.25
},
{
"num_generacio" : 125,
"fitness" : 189.3
}
],
"màxim_fitness" :192.75,
"millor_ocell" :
{
"neurones_input" : 3,
"neurones_amagades" :0,
"neuornes_output" :1,
"conexions" : [
{
"desde" :0,
"fins" :3,
"importancia" :0.72370946407318},
{
"desde" :1,
"fins" :3,
"importancia" :0.90157687664032},
{
"desde" :2,
"fins" :3,
"importancia" :-0.73218309879303}
]
}
},
{
"num_partida" :6,
"generacions" :
[
{
"num_generacio" : 1,
"fitness" : 50.35
},
{
"num_generacio" : 2,
"fitness" : 113.75
},
{
"num_generacio" : 3,
"fitness" : 142.05
},
{
"num_generacio" : 4,
"fitness" : 1162.9
},
{
"num_generacio" : 5,
"fitness" : 180
},
{
"num_generacio" : 6,
"fitness" : 2327.05
},
{
"num_generacio" : 7,
"fitness" : 152.5
},
{
"num_generacio" : 8,
"fitness" : 2291.25
},
{
"num_generacio" : 9,
"fitness" : 140.5
},
{
"num_generacio" : 10,
"fitness" : 164670.099999997
},
{
"num_generacio" : 11,
"fitness" : 77.8499999999999
},
{
"num_generacio" : 12,
"fitness" : 128835.000000008
},
{
"num_generacio" : 13,
"fitness" : 164877.649999997
},
{
"num_generacio" : 14,
"fitness" : 137094.650000006
},
{
"num_generacio" : 15,
"fitness" : 164655.449999997
},
{
"num_generacio" : 16,
"fitness" : 164899.149999997
},
{
"num_generacio" : 17,
"fitness" : 164755.199999997
}
],
"màxim_fitness" :164899.149999997,
"millor_ocell" :
{
"neurones_input" : 3,
"neurones_amagades" :0,
"neuornes_output" :1,
"conexions" : [
{
"desde" :0,
"fins" :3,
"importancia" :0.84435546398163},
{
"desde" :1,
"fins" :3,
"importancia" :-0.80799841880798},
{
"desde" :2,
"fins" :3,
"importancia" :-0.17570686340332}
]
}
},
{
"num_partida" :7,
"generacions" :
[
{
"num_generacio" : 1,
"fitness" : 82.9999999999999
},
{
"num_generacio" : 2,
"fitness" : 141.5
},
{
"num_generacio" : 3,
"fitness" : 125.5
},
{
"num_generacio" : 4,
"fitness" : 131.75
},
{
"num_generacio" : 5,
"fitness" : 123
},
{
"num_generacio" : 6,
"fitness" : 125
},
{
"num_generacio" : 7,
"fitness" : 141.75
},
{
"num_generacio" : 8,
"fitness" : 140.75
},
{
"num_generacio" : 9,
"fitness" : 217.25
},
{
"num_generacio" : 10,
"fitness" : 201.25
},
{
"num_generacio" : 11,
"fitness" : 159.25
},
{
"num_generacio" : 12,
"fitness" : 133.75
},
{
"num_generacio" : 13,
"fitness" : 133.75
},
{
"num_generacio" : 14,
"fitness" : 155.75
},
{
"num_generacio" : 15,
"fitness" : 210.75
},
{
"num_generacio" : 16,
"fitness" : 212.5
},
{
"num_generacio" : 17,
"fitness" : 159.25
},
{
"num_generacio" : 18,
"fitness" : 133
},
{
"num_generacio" : 19,
"fitness" : 199.5
},
{
"num_generacio" : 20,
"fitness" : 132.25
},
{
"num_generacio" : 21,
"fitness" : 135
},
{
"num_generacio" : 22,
"fitness" : 134.25
},
{
"num_generacio" : 23,
"fitness" : 191
},
{
"num_generacio" : 24,
"fitness" : 215
},
{
"num_generacio" : 25,
"fitness" : 208
},
{
"num_generacio" : 26,
"fitness" : 133
},
{
"num_generacio" : 27,
"fitness" : 135.25
},
{
"num_generacio" : 28,
"fitness" : 198.5
},
{
"num_generacio" : 29,
"fitness" : 133
},
{
"num_generacio" : 30,
"fitness" : 176.25
},
{
"num_generacio" : 31,
"fitness" : 163.75
},
{
"num_generacio" : 32,
"fitness" : 133.75
},
{
"num_generacio" : 33,
"fitness" : 209
},
{
"num_generacio" : 34,
"fitness" : 207.5
},
{
"num_generacio" : 35,
"fitness" : 172.25
},
{
"num_generacio" : 36,
"fitness" : 208.3
},
{
"num_generacio" : 37,
"fitness" : 133
},
{
"num_generacio" : 38,
"fitness" : 132.5
},
{
"num_generacio" : 39,
"fitness" : 131.5
},
{
"num_generacio" : 40,
"fitness" : 176.5
},
{
"num_generacio" : 41,
"fitness" : 133.5
},
{
"num_generacio" : 42,
"fitness" : 135
},
{
"num_generacio" : 43,
"fitness" : 208
},
{
"num_generacio" : 44,
"fitness" : 212
},
{
"num_generacio" : 45,
"fitness" : 201.75
},
{
"num_generacio" : 46,
"fitness" : 213.6
},
{
"num_generacio" : 47,
"fitness" : 138.75
},
{
"num_generacio" : 48,
"fitness" : 214.25
},
{
"num_generacio" : 49,
"fitness" : 134.75
},
{
"num_generacio" : 50,
"fitness" : 196.35
},
{
"num_generacio" : 51,
"fitness" : 143.25
},
{
"num_generacio" : 52,
"fitness" : 151.2
},
{
"num_generacio" : 53,
"fitness" : 210.25
},
{
"num_generacio" : 54,
"fitness" : 133.25
},
{
"num_generacio" : 55,
"fitness" : 196
},
{
"num_generacio" : 56,
"fitness" : 180.25
},
{
"num_generacio" : 57,
"fitness" : 217.25
},
{
"num_generacio" : 58,
"fitness" : 216.75
},
{
"num_generacio" : 59,
"fitness" : 200
},
{
"num_generacio" : 60,
"fitness" : 134.5
},
{
"num_generacio" : 61,
"fitness" : 163
},
{
"num_generacio" : 62,
"fitness" : 176.5
},
{
"num_generacio" : 63,
"fitness" : 133.25
},
{
"num_generacio" : 64,
"fitness" : 147.75
},
{
"num_generacio" : 65,
"fitness" : 133
},
{
"num_generacio" : 66,
"fitness" : 133.25
},
{
"num_generacio" : 67,
"fitness" : 180.25
},
{
"num_generacio" : 68,
"fitness" : 202.25
},
{
"num_generacio" : 69,
"fitness" : 201
},
{
"num_generacio" : 70,
"fitness" : 161.5
},
{
"num_generacio" : 71,
"fitness" : 134
},
{
"num_generacio" : 72,
"fitness" : 147.75
},
{
"num_generacio" : 73,
"fitness" : 131
},
{
"num_generacio" : 74,
"fitness" : 131.75
},
{
"num_generacio" : 75,
"fitness" : 209.25
},
{
"num_generacio" : 76,
"fitness" : 210.75
},
{
"num_generacio" : 77,
"fitness" : 194.15
},
{
"num_generacio" : 78,
"fitness" : 156
},
{
"num_generacio" : 79,
"fitness" : 147.75
},
{
"num_generacio" : 80,
"fitness" : 204.25
},
{
"num_generacio" : 81,
"fitness" : 133
},
{
"num_generacio" : 82,
"fitness" : 143.75
},
{
"num_generacio" : 83,
"fitness" : 156.95
},
{
"num_generacio" : 84,
"fitness" : 204.5
},
{
"num_generacio" : 85,
"fitness" : 132.25
},
{
"num_generacio" : 86,
"fitness" : 211.75
},
{
"num_generacio" : 87,
"fitness" : 164.75
},
{
"num_generacio" : 88,
"fitness" : 205.85
},
{
"num_generacio" : 89,
"fitness" : 196.5
},
{
"num_generacio" : 90,
"fitness" : 150.95
},
{
"num_generacio" : 91,
"fitness" : 203.75
},
{
"num_generacio" : 92,
"fitness" : 139
},
{
"num_generacio" : 93,
"fitness" : 175
},
{
"num_generacio" : 94,
"fitness" : 135.45
},
{
"num_generacio" : 95,
"fitness" : 158.5
},
{
"num_generacio" : 96,
"fitness" : 204.5
},
{
"num_generacio" : 97,
"fitness" : 156.5
},
{
"num_generacio" : 98,
"fitness" : 214.55
},
{
"num_generacio" : 99,
"fitness" : 135.25
},
{
"num_generacio" : 100,
"fitness" : 183.25
},
{
"num_generacio" : 101,
"fitness" : 197.5
},
{
"num_generacio" : 102,
"fitness" : 208.75
},
{
"num_generacio" : 103,
"fitness" : 157
},
{
"num_generacio" : 104,
"fitness" : 191.5
},
{
"num_generacio" : 105,
"fitness" : 132
},
{
"num_generacio" : 106,
"fitness" : 132
},
{
"num_generacio" : 107,
"fitness" : 132.5
},
{
"num_generacio" : 108,
"fitness" : 207.25
},
{
"num_generacio" : 109,
"fitness" : 148.25
},
{
"num_generacio" : 110,
"fitness" : 130.45
},
{
"num_generacio" : 111,
"fitness" : 177.45
},
{
"num_generacio" : 112,
"fitness" : 157.2
},
{
"num_generacio" : 113,
"fitness" : 192.2
},
{
"num_generacio" : 114,
"fitness" : 144.45
},
{
"num_generacio" : 115,
"fitness" : 207.95
},
{
"num_generacio" : 116,
"fitness" : 169.2
},
{
"num_generacio" : 117,
"fitness" : 188.2
},
{
"num_generacio" : 118,
"fitness" : 201.05
},
{
"num_generacio" : 119,
"fitness" : 129.95
},
{
"num_generacio" : 120,
"fitness" : 203.45
},
{
"num_generacio" : 121,
"fitness" : 144.2
},
{
"num_generacio" : 122,
"fitness" : 134.95
},
{
"num_generacio" : 123,
"fitness" : 173.2
},
{
"num_generacio" : 124,
"fitness" : 129.7
},
{
"num_generacio" : 125,
"fitness" : 152.7
}
],
"màxim_fitness" :217.25,
"millor_ocell" :
{
"neurones_input" : 3,
"neurones_amagades" :0,
"neuornes_output" :1,
"conexions" : [
{
"desde" :0,
"fins" :3,
"importancia" :0.8229238986969},
{
"desde" :1,
"fins" :3,
"importancia" :0.47530770301819},
{
"desde" :2,
"fins" :3,
"importancia" :-0.59437537193298}
]
}
},
{
"num_partida" :8,
"generacions" :
[
{
"num_generacio" : 1,
"fitness" : 25.5
},
{
"num_generacio" : 2,
"fitness" : 25.5
},
{
"num_generacio" : 3,
"fitness" : 39.95
},
{
"num_generacio" : 4,
"fitness" : 75.7499999999999
},
{
"num_generacio" : 5,
"fitness" : 64.1999999999999
},
{
"num_generacio" : 6,
"fitness" : 9058.10000000002
},
{
"num_generacio" : 7,
"fitness" : 31130.6999999995
},
{
"num_generacio" : 8,
"fitness" : 4613.10000000001
},
{
"num_generacio" : 9,
"fitness" : 15612.8999999999
},
{
"num_generacio" : 10,
"fitness" : 11024.95
},
{
"num_generacio" : 11,
"fitness" : 3449.10000000001
},
{
"num_generacio" : 12,
"fitness" : 4579.40000000002
},
{
"num_generacio" : 13,
"fitness" : 12297
},
{
"num_generacio" : 14,
"fitness" : 36415.5499999999
},
{
"num_generacio" : 15,
"fitness" : 5732.20000000002
},
{
"num_generacio" : 16,
"fitness" : 15559.1999999999
},
{
"num_generacio" : 17,
"fitness" : 88071.2500000043
},
{
"num_generacio" : 18,
"fitness" : 22090.0499999997
},
{
"num_generacio" : 19,
"fitness" : 36504.7999999999
},
{
"num_generacio" : 20,
"fitness" : 6777.65000000003
},
{
"num_generacio" : 21,
"fitness" : 17648.1499999998
},
{
"num_generacio" : 22,
"fitness" : 3494.95000000001
},
{
"num_generacio" : 23,
"fitness" : 24301.8999999997
},
{
"num_generacio" : 24,
"fitness" : 25402.3499999997
},
{
"num_generacio" : 25,
"fitness" : 26493.9999999996
},
{
"num_generacio" : 26,
"fitness" : 164777.249999997
},
{
"num_generacio" : 27,
"fitness" : 164848.199999997
},
{
"num_generacio" : 28,
"fitness" : 64614.3000000023
},
{
"num_generacio" : 29,
"fitness" : 20998.7499999998
},
{
"num_generacio" : 30,
"fitness" : 164272.299999997
},
{
"num_generacio" : 31,
"fitness" : 86558.0500000042
},
{
"num_generacio" : 32,
"fitness" : 22124.6499999997
},
{
"num_generacio" : 33,
"fitness" : 164457.449999997
},
{
"num_generacio" : 34,
"fitness" : 118137.400000007
},
{
"num_generacio" : 35,
"fitness" : 83132.5000000039
},
{
"num_generacio" : 36,
"fitness" : 164581.049999997
},
{
"num_generacio" : 37,
"fitness" : 164635.549999997
},
{
"num_generacio" : 38,
"fitness" : 163740.849999997
}
],
"màxim_fitness" :164848.199999997,
"millor_ocell" :
{
"neurones_input" : 3,
"neurones_amagades" :0,
"neuornes_output" :1,
"conexions" : [
{
"desde" :0,
"fins" :3,
"importancia" :0.85162651538849},
{
"desde" :1,
"fins" :3,
"importancia" :-0.84033709764481},
{
"desde" :2,
"fins" :3,
"importancia" :-0.14819687604904}
]
}
},
{
"num_partida" :9,
"generacions" :
[
{
"num_generacio" : 1,
"fitness" : 11873.1499999999
},
{
"num_generacio" : 2,
"fitness" : 15070.1499999999
},
{
"num_generacio" : 3,
"fitness" : 8658.20000000002
},
{
"num_generacio" : 4,
"fitness" : 2254.6
},
{
"num_generacio" : 5,
"fitness" : 2260.95
},
{
"num_generacio" : 6,
"fitness" : 6558.50000000003
},
{
"num_generacio" : 7,
"fitness" : 3364.50000000001
},
{
"num_generacio" : 8,
"fitness" : 7615.85000000003
},
{
"num_generacio" : 9,
"fitness" : 1113.5
},
{
"num_generacio" : 10,
"fitness" : 7581.75000000003
},
{
"num_generacio" : 11,
"fitness" : 6524.25000000003
},
{
"num_generacio" : 12,
"fitness" : 1155.1
},
{
"num_generacio" : 13,
"fitness" : 150.7
},
{
"num_generacio" : 14,
"fitness" : 5479.25000000002
},
{
"num_generacio" : 15,
"fitness" : 25947.8499999996
},
{
"num_generacio" : 16,
"fitness" : 3356.35000000001
},
{
"num_generacio" : 17,
"fitness" : 4352.95000000002
},
{
"num_generacio" : 18,
"fitness" : 2153
},
{
"num_generacio" : 19,
"fitness" : 128.25
},
{
"num_generacio" : 20,
"fitness" : 1267.25
},
{
"num_generacio" : 21,
"fitness" : 7668.65000000003
},
{
"num_generacio" : 22,
"fitness" : 20611.0999999998
},
{
"num_generacio" : 23,
"fitness" : 1159.6
},
{
"num_generacio" : 24,
"fitness" : 4328.60000000001
},
{
"num_generacio" : 25,
"fitness" : 2308.45
},
{
"num_generacio" : 26,
"fitness" : 9689.19999999999
},
{
"num_generacio" : 27,
"fitness" : 1214.9
},
{
"num_generacio" : 28,
"fitness" : 3279.20000000001
},
{
"num_generacio" : 29,
"fitness" : 10859.2
},
{
"num_generacio" : 30,
"fitness" : 1130.65
},
{
"num_generacio" : 31,
"fitness" : 1161.6
},
{
"num_generacio" : 32,
"fitness" : 5430.85000000002
},
{
"num_generacio" : 33,
"fitness" : 3329.60000000001
},
{
"num_generacio" : 34,
"fitness" : 110.85
},
{
"num_generacio" : 35,
"fitness" : 3337.50000000001
},
{
"num_generacio" : 36,
"fitness" : 6551.40000000003
},
{
"num_generacio" : 37,
"fitness" : 2200.35
},
{
"num_generacio" : 38,
"fitness" : 77.4
},
{
"num_generacio" : 39,
"fitness" : 3351.95000000001
},
{
"num_generacio" : 40,
"fitness" : 3257.50000000001
},
{
"num_generacio" : 41,
"fitness" : 8658.75000000002
},
{
"num_generacio" : 42,
"fitness" : 4440.10000000002
},
{
"num_generacio" : 43,
"fitness" : 1132.4
},
{
"num_generacio" : 44,
"fitness" : 2219.65
},
{
"num_generacio" : 45,
"fitness" : 6526.75000000003
},
{
"num_generacio" : 46,
"fitness" : 6613.75000000003
},
{
"num_generacio" : 47,
"fitness" : 10963.85
},
{
"num_generacio" : 48,
"fitness" : 3555.65000000001
},
{
"num_generacio" : 49,
"fitness" : 17668.4999999998
},
{
"num_generacio" : 50,
"fitness" : 6817.40000000003
},
{
"num_generacio" : 51,
"fitness" : 1309.95
},
{
"num_generacio" : 52,
"fitness" : 2428.05
},
{
"num_generacio" : 53,
"fitness" : 1330.85
},
{
"num_generacio" : 54,
"fitness" : 42589.9500000004
},
{
"num_generacio" : 55,
"fitness" : 163749.449999997
},
{
"num_generacio" : 56,
"fitness" : 30616.7499999995
},
{
"num_generacio" : 57,
"fitness" : 163806.649999997
},
{
"num_generacio" : 58,
"fitness" : 164723.599999997
},
{
"num_generacio" : 59,
"fitness" : 164874.699999997
}
],
"màxim_fitness" :164874.699999997,
"millor_ocell" :
{
"neurones_input" : 3,
"neurones_amagades" :0,
"neuornes_output" :1,
"conexions" : [
{
"desde" :0,
"fins" :3,
"importancia" :0.684046626091},
{
"desde" :1,
"fins" :3,
"importancia" :-0.66382443904877},
{
"desde" :2,
"fins" :3,
"importancia" :-0.13418900966644}
]
}
},
{
"num_partida" :10,
"generacions" :
[
{
"num_generacio" : 1,
"fitness" : 1151.65
},
{
"num_generacio" : 2,
"fitness" : 1167.7
},
{
"num_generacio" : 3,
"fitness" : 136
},
{
"num_generacio" : 4,
"fitness" : 139.75
},
{
"num_generacio" : 5,
"fitness" : 139.75
},
{
"num_generacio" : 6,
"fitness" : 166.25
},
{
"num_generacio" : 7,
"fitness" : 227
},
{
"num_generacio" : 8,
"fitness" : 280.100000000001
},
{
"num_generacio" : 9,
"fitness" : 285.450000000001
},
{
"num_generacio" : 10,
"fitness" : 203.5
},
{
"num_generacio" : 11,
"fitness" : 147.25
},
{
"num_generacio" : 12,
"fitness" : 146
},
{
"num_generacio" : 13,
"fitness" : 153.75
},
{
"num_generacio" : 14,
"fitness" : 258.5
},
{
"num_generacio" : 15,
"fitness" : 282.400000000001
},
{
"num_generacio" : 16,
"fitness" : 145
},
{
"num_generacio" : 17,
"fitness" : 185
},
{
"num_generacio" : 18,
"fitness" : 258.6
},
{
"num_generacio" : 19,
"fitness" : 214.15
},
{
"num_generacio" : 20,
"fitness" : 214.15
},
{
"num_generacio" : 21,
"fitness" : 185.25
},
{
"num_generacio" : 22,
"fitness" : 212.6
},
{
"num_generacio" : 23,
"fitness" : 187
},
{
"num_generacio" : 24,
"fitness" : 1267.45
},
{
"num_generacio" : 25,
"fitness" : 197
},
{
"num_generacio" : 26,
"fitness" : 3494.70000000001
},
{
"num_generacio" : 27,
"fitness" : 206
},
{
"num_generacio" : 28,
"fitness" : 190
},
{
"num_generacio" : 29,
"fitness" : 15496.9499999999
},
{
"num_generacio" : 30,
"fitness" : 13209.1499999999
},
{
"num_generacio" : 31,
"fitness" : 14400.5499999999
},
{
"num_generacio" : 32,
"fitness" : 164366.699999997
},
{
"num_generacio" : 33,
"fitness" : 164580.599999997
},
{
"num_generacio" : 34,
"fitness" : 7760.65000000003
},
{
"num_generacio" : 35,
"fitness" : 129.7
},
{
"num_generacio" : 36,
"fitness" : 17571.4999999998
},
{
"num_generacio" : 37,
"fitness" : 35031.6499999997
},
{
"num_generacio" : 38,
"fitness" : 93193.7000000048
},
{
"num_generacio" : 39,
"fitness" : 70703.3500000029
},
{
"num_generacio" : 40,
"fitness" : 162354.799999997
},
{
"num_generacio" : 41,
"fitness" : 18580.1999999998
},
{
"num_generacio" : 42,
"fitness" : 73816.1500000031
},
{
"num_generacio" : 43,
"fitness" : 6857.30000000003
},
{
"num_generacio" : 44,
"fitness" : 162326.949999997
},
{
"num_generacio" : 45,
"fitness" : 6635.10000000003
},
{
"num_generacio" : 46,
"fitness" : 39068.9
},
{
"num_generacio" : 47,
"fitness" : 162511.599999997
},
{
"num_generacio" : 48,
"fitness" : 162490.699999997
},
{
"num_generacio" : 49,
"fitness" : 48304.9000000009
},
{
"num_generacio" : 50,
"fitness" : 163290.299999997
},
{
"num_generacio" : 51,
"fitness" : 90285.4500000047
},
{
"num_generacio" : 52,
"fitness" : 92666.8000000048
},
{
"num_generacio" : 53,
"fitness" : 163550.949999997
},
{
"num_generacio" : 54,
"fitness" : 105749.250000006
},
{
"num_generacio" : 55,
"fitness" : 54507.0000000014
},
{
"num_generacio" : 56,
"fitness" : 163245.199999997
},
{
"num_generacio" : 57,
"fitness" : 163881.899999997
},
{
"num_generacio" : 58,
"fitness" : 98274.2500000053
},
{
"num_generacio" : 59,
"fitness" : 62230.5000000022
},
{
"num_generacio" : 60,
"fitness" : 163034.949999997
},
{
"num_generacio" : 61,
"fitness" : 44672.1000000005
},
{
"num_generacio" : 62,
"fitness" : 163106.449999997
},
{
"num_generacio" : 63,
"fitness" : 163683.449999997
},
{
"num_generacio" : 64,
"fitness" : 163586.399999997
}
],
"màxim_fitness" :164580.599999997,
"millor_ocell" :
{
"neurones_input" : 3,
"neurones_amagades" :0,
"neuornes_output" :1,
"conexions" : [
{
"desde" :0,
"fins" :3,
"importancia" :0.7556608915329},
{
"desde" :1,
"fins" :3,
"importancia" :-0.71634924411774},
{
"desde" :2,
"fins" :3,
"importancia" :-0.21716690063477}
]
}
},
{
"num_partida" :11,
"generacions" :
[
{
"num_generacio" : 1,
"fitness" : 83.2499999999998
},
{
"num_generacio" : 2,
"fitness" : 109.5
},
{
"num_generacio" : 3,
"fitness" : 108.75
},
{
"num_generacio" : 4,
"fitness" : 175.25
},
{
"num_generacio" : 5,
"fitness" : 135.25
},
{
"num_generacio" : 6,
"fitness" : 138
},
{
"num_generacio" : 7,
"fitness" : 131.25
},
{
"num_generacio" : 8,
"fitness" : 150
},
{
"num_generacio" : 9,
"fitness" : 150.25
},
{
"num_generacio" : 10,
"fitness" : 158.25
},
{
"num_generacio" : 11,
"fitness" : 135
},
{
"num_generacio" : 12,
"fitness" : 152.5
},
{
"num_generacio" : 13,
"fitness" : 178.25
},
{
"num_generacio" : 14,
"fitness" : 158
},
{
"num_generacio" : 15,
"fitness" : 150.25
},
{
"num_generacio" : 16,
"fitness" : 152.5
},
{
"num_generacio" : 17,
"fitness" : 132.25
},
{
"num_generacio" : 18,
"fitness" : 178
},
{
"num_generacio" : 19,
"fitness" : 135.25
},
{
"num_generacio" : 20,
"fitness" : 147.75
},
{
"num_generacio" : 21,
"fitness" : 150
},
{
"num_generacio" : 22,
"fitness" : 175.5
},
{
"num_generacio" : 23,
"fitness" : 132.25
},
{
"num_generacio" : 24,
"fitness" : 150.25
},
{
"num_generacio" : 25,
"fitness" : 153.25
},
{
"num_generacio" : 26,
"fitness" : 150
},
{
"num_generacio" : 27,
"fitness" : 131
},
{
"num_generacio" : 28,
"fitness" : 132
},
{
"num_generacio" : 29,
"fitness" : 160.25
},
{
"num_generacio" : 30,
"fitness" : 172.75
},
{
"num_generacio" : 31,
"fitness" : 180.75
},
{
"num_generacio" : 32,
"fitness" : 148
},
{
"num_generacio" : 33,
"fitness" : 180
},
{
"num_generacio" : 34,
"fitness" : 156.25
},
{
"num_generacio" : 35,
"fitness" : 175.25
},
{
"num_generacio" : 36,
"fitness" : 140.25
},
{
"num_generacio" : 37,
"fitness" : 132.25
},
{
"num_generacio" : 38,
"fitness" : 138
},
{
"num_generacio" : 39,
"fitness" : 152.5
},
{
"num_generacio" : 40,
"fitness" : 159.75
},
{
"num_generacio" : 41,
"fitness" : 153
},
{
"num_generacio" : 42,
"fitness" : 173.75
},
{
"num_generacio" : 43,
"fitness" : 140.5
},
{
"num_generacio" : 44,
"fitness" : 158.75
},
{
"num_generacio" : 45,
"fitness" : 175.5
},
{
"num_generacio" : 46,
"fitness" : 175.75
},
{
"num_generacio" : 47,
"fitness" : 153
},
{
"num_generacio" : 48,
"fitness" : 131.75
},
{
"num_generacio" : 49,
"fitness" : 159
},
{
"num_generacio" : 50,
"fitness" : 175.5
},
{
"num_generacio" : 51,
"fitness" : 155.75
},
{
"num_generacio" : 52,
"fitness" : 145.5
},
{
"num_generacio" : 53,
"fitness" : 181.5
},
{
"num_generacio" : 54,
"fitness" : 155.25
},
{
"num_generacio" : 55,
"fitness" : 150.25
},
{
"num_generacio" : 56,
"fitness" : 184.75
},
{
"num_generacio" : 57,
"fitness" : 177.5
},
{
"num_generacio" : 58,
"fitness" : 162.5
},
{
"num_generacio" : 59,
"fitness" : 177.05
},
{
"num_generacio" : 60,
"fitness" : 148
},
{
"num_generacio" : 61,
"fitness" : 179.75
},
{
"num_generacio" : 62,
"fitness" : 152.5
},
{
"num_generacio" : 63,
"fitness" : 178.5
},
{
"num_generacio" : 64,
"fitness" : 179.75
},
{
"num_generacio" : 65,
"fitness" : 185
},
{
"num_generacio" : 66,
"fitness" : 155.75
},
{
"num_generacio" : 67,
"fitness" : 140.5
},
{
"num_generacio" : 68,
"fitness" : 180.75
},
{
"num_generacio" : 69,
"fitness" : 177
},
{
"num_generacio" : 70,
"fitness" : 137.75
},
{
"num_generacio" : 71,
"fitness" : 147.5
},
{
"num_generacio" : 72,
"fitness" : 181
},
{
"num_generacio" : 73,
"fitness" : 135.75
},
{
"num_generacio" : 74,
"fitness" : 156.5
},
{
"num_generacio" : 75,
"fitness" : 138
},
{
"num_generacio" : 76,
"fitness" : 182.75
},
{
"num_generacio" : 77,
"fitness" : 135.5
},
{
"num_generacio" : 78,
"fitness" : 133.25
},
{
"num_generacio" : 79,
"fitness" : 181
},
{
"num_generacio" : 80,
"fitness" : 174.5
},
{
"num_generacio" : 81,
"fitness" : 182.5
},
{
"num_generacio" : 82,
"fitness" : 182
},
{
"num_generacio" : 83,
"fitness" : 155.75
},
{
"num_generacio" : 84,
"fitness" : 143
},
{
"num_generacio" : 85,
"fitness" : 143
},
{
"num_generacio" : 86,
"fitness" : 160
},
{
"num_generacio" : 87,
"fitness" : 152.95
},
{
"num_generacio" : 88,
"fitness" : 167.5
},
{
"num_generacio" : 89,
"fitness" : 136
},
{
"num_generacio" : 90,
"fitness" : 133
},
{
"num_generacio" : 91,
"fitness" : 179.75
},
{
"num_generacio" : 92,
"fitness" : 156.25
},
{
"num_generacio" : 93,
"fitness" : 154.5
},
{
"num_generacio" : 94,
"fitness" : 133
},
{
"num_generacio" : 95,
"fitness" : 135.5
},
{
"num_generacio" : 96,
"fitness" : 150.75
},
{
"num_generacio" : 97,
"fitness" : 138.25
},
{
"num_generacio" : 98,
"fitness" : 153
},
{
"num_generacio" : 99,
"fitness" : 151
},
{
"num_generacio" : 100,
"fitness" : 133.75
},
{
"num_generacio" : 101,
"fitness" : 179.25
},
{
"num_generacio" : 102,
"fitness" : 180.5
},
{
"num_generacio" : 103,
"fitness" : 151.75
},
{
"num_generacio" : 104,
"fitness" : 146
},
{
"num_generacio" : 105,
"fitness" : 143.25
},
{
"num_generacio" : 106,
"fitness" : 135.5
},
{
"num_generacio" : 107,
"fitness" : 133.5
},
{
"num_generacio" : 108,
"fitness" : 133.25
},
{
"num_generacio" : 109,
"fitness" : 179.75
},
{
"num_generacio" : 110,
"fitness" : 157
},
{
"num_generacio" : 111,
"fitness" : 133.25
},
{
"num_generacio" : 112,
"fitness" : 133.25
},
{
"num_generacio" : 113,
"fitness" : 138.5
},
{
"num_generacio" : 114,
"fitness" : 133.75
},
{
"num_generacio" : 115,
"fitness" : 133
},
{
"num_generacio" : 116,
"fitness" : 148.25
},
{
"num_generacio" : 117,
"fitness" : 186.5
},
{
"num_generacio" : 118,
"fitness" : 145.75
},
{
"num_generacio" : 119,
"fitness" : 177.75
},
{
"num_generacio" : 120,
"fitness" : 180.25
},
{
"num_generacio" : 121,
"fitness" : 180.25
},
{
"num_generacio" : 122,
"fitness" : 155.5
},
{
"num_generacio" : 123,
"fitness" : 156.5
},
{
"num_generacio" : 124,
"fitness" : 133
},
{
"num_generacio" : 125,
"fitness" : 135.25
}
],
"màxim_fitness" :186.5,
"millor_ocell" :
{
"neurones_input" : 3,
"neurones_amagades" :0,
"neuornes_output" :1,
"conexions" : [
{
"desde" :0,
"fins" :3,
"importancia" :0.56891679763794},
{
"desde" :1,
"fins" :3,
"importancia" :0.9873970746994},
{
"desde" :2,
"fins" :3,
"importancia" :-0.68831384181976}
]
}
},
{
"num_partida" :12,
"generacions" :
[
{
"num_generacio" : 1,
"fitness" : 25.5
},
{
"num_generacio" : 2,
"fitness" : 25.5
},
{
"num_generacio" : 3,
"fitness" : 25.5
},
{
"num_generacio" : 4,
"fitness" : 25.5
},
{
"num_generacio" : 5,
"fitness" : 25.5
},
{
"num_generacio" : 6,
"fitness" : 25.5
},
{
"num_generacio" : 7,
"fitness" : 113.25
},
{
"num_generacio" : 8,
"fitness" : 103
},
{
"num_generacio" : 9,
"fitness" : 130.5
},
{
"num_generacio" : 10,
"fitness" : 132.25
},
{
"num_generacio" : 11,
"fitness" : 1172.45
},
{
"num_generacio" : 12,
"fitness" : 158
},
{
"num_generacio" : 13,
"fitness" : 2428.65
},
{
"num_generacio" : 14,
"fitness" : 4505.50000000002
},
{
"num_generacio" : 15,
"fitness" : 1299.95
},
{
"num_generacio" : 16,
"fitness" : 1286.45
},
{
"num_generacio" : 17,
"fitness" : 262.9
},
{
"num_generacio" : 18,
"fitness" : 9982.99999999999
},
{
"num_generacio" : 19,
"fitness" : 11190.55
},
{
"num_generacio" : 20,
"fitness" : 2380.95
},
{
"num_generacio" : 21,
"fitness" : 3475.35000000001
},
{
"num_generacio" : 22,
"fitness" : 14390.9999999999
},
{
"num_generacio" : 23,
"fitness" : 3445.55000000001
},
{
"num_generacio" : 24,
"fitness" : 8989.20000000002
},
{
"num_generacio" : 25,
"fitness" : 7832.70000000003
},
{
"num_generacio" : 26,
"fitness" : 164173.449999997
},
{
"num_generacio" : 27,
"fitness" : 163988.299999997
},
{
"num_generacio" : 28,
"fitness" : 163929.949999997
}
],
"màxim_fitness" :164173.449999997,
"millor_ocell" :
{
"neurones_input" : 3,
"neurones_amagades" :0,
"neuornes_output" :1,
"conexions" : [
{
"desde" :0,
"fins" :3,
"importancia" :0.26048684120178},
{
"desde" :1,
"fins" :3,
"importancia" :-0.2640797495842},
{
"desde" :2,
"fins" :3,
"importancia" :-0.00722521543503}
]
}
},
{
"num_partida" :13,
"generacions" :
[
{
"num_generacio" : 1,
"fitness" : 25.5
},
{
"num_generacio" : 2,
"fitness" : 25.5
},
{
"num_generacio" : 3,
"fitness" : 25.5
},
{
"num_generacio" : 4,
"fitness" : 25.5
},
{
"num_generacio" : 5,
"fitness" : 25.5
},
{
"num_generacio" : 6,
"fitness" : 118
},
{
"num_generacio" : 7,
"fitness" : 102.75
},
{
"num_generacio" : 8,
"fitness" : 92.4999999999998
},
{
"num_generacio" : 9,
"fitness" : 161
},
{
"num_generacio" : 10,
"fitness" : 166.25
},
{
"num_generacio" : 11,
"fitness" : 145
},
{
"num_generacio" : 12,
"fitness" : 177
},
{
"num_generacio" : 13,
"fitness" : 144.75
},
{
"num_generacio" : 14,
"fitness" : 124.75
},
{
"num_generacio" : 15,
"fitness" : 123.25
},
{
"num_generacio" : 16,
"fitness" : 123.25
},
{
"num_generacio" : 17,
"fitness" : 138.5
},
{
"num_generacio" : 18,
"fitness" : 188.5
},
{
"num_generacio" : 19,
"fitness" : 183.5
},
{
"num_generacio" : 20,
"fitness" : 187.75
},
{
"num_generacio" : 21,
"fitness" : 188.75
},
{
"num_generacio" : 22,
"fitness" : 165
},
{
"num_generacio" : 23,
"fitness" : 127.75
},
{
"num_generacio" : 24,
"fitness" : 123
},
{
"num_generacio" : 25,
"fitness" : 186.25
},
{
"num_generacio" : 26,
"fitness" : 167.25
},
{
"num_generacio" : 27,
"fitness" : 125
},
{
"num_generacio" : 28,
"fitness" : 132.25
},
{
"num_generacio" : 29,
"fitness" : 137.75
},
{
"num_generacio" : 30,
"fitness" : 153.5
},
{
"num_generacio" : 31,
"fitness" : 145.5
},
{
"num_generacio" : 32,
"fitness" : 133
},
{
"num_generacio" : 33,
"fitness" : 148.75
},
{
"num_generacio" : 34,
"fitness" : 186.25
},
{
"num_generacio" : 35,
"fitness" : 185.5
},
{
"num_generacio" : 36,
"fitness" : 131.5
},
{
"num_generacio" : 37,
"fitness" : 150.5
},
{
"num_generacio" : 38,
"fitness" : 135.25
},
{
"num_generacio" : 39,
"fitness" : 161.25
},
{
"num_generacio" : 40,
"fitness" : 153.75
},
{
"num_generacio" : 41,
"fitness" : 195.5
},
{
"num_generacio" : 42,
"fitness" : 185.25
},
{
"num_generacio" : 43,
"fitness" : 197.25
},
{
"num_generacio" : 44,
"fitness" : 140.25
},
{
"num_generacio" : 45,
"fitness" : 148.75
},
{
"num_generacio" : 46,
"fitness" : 153.5
},
{
"num_generacio" : 47,
"fitness" : 140
},
{
"num_generacio" : 48,
"fitness" : 170.25
},
{
"num_generacio" : 49,
"fitness" : 157.25
},
{
"num_generacio" : 50,
"fitness" : 137.75
},
{
"num_generacio" : 51,
"fitness" : 131.5
},
{
"num_generacio" : 52,
"fitness" : 140.5
},
{
"num_generacio" : 53,
"fitness" : 131.5
},
{
"num_generacio" : 54,
"fitness" : 190.75
},
{
"num_generacio" : 55,
"fitness" : 165.75
},
{
"num_generacio" : 56,
"fitness" : 145.5
},
{
"num_generacio" : 57,
"fitness" : 196.5
},
{
"num_generacio" : 58,
"fitness" : 137.75
},
{
"num_generacio" : 59,
"fitness" : 145.25
},
{
"num_generacio" : 60,
"fitness" : 132.25
},
{
"num_generacio" : 61,
"fitness" : 138
},
{
"num_generacio" : 62,
"fitness" : 155.75
},
{
"num_generacio" : 63,
"fitness" : 140
},
{
"num_generacio" : 64,
"fitness" : 183.25
},
{
"num_generacio" : 65,
"fitness" : 193.75
},
{
"num_generacio" : 66,
"fitness" : 193.75
},
{
"num_generacio" : 67,
"fitness" : 131.75
},
{
"num_generacio" : 68,
"fitness" : 183.25
},
{
"num_generacio" : 69,
"fitness" : 189.5
},
{
"num_generacio" : 70,
"fitness" : 156
},
{
"num_generacio" : 71,
"fitness" : 154
},
{
"num_generacio" : 72,
"fitness" : 156.75
},
{
"num_generacio" : 73,
"fitness" : 187.75
},
{
"num_generacio" : 74,
"fitness" : 132.25
},
{
"num_generacio" : 75,
"fitness" : 145.25
},
{
"num_generacio" : 76,
"fitness" : 131.25
},
{
"num_generacio" : 77,
"fitness" : 194
},
{
"num_generacio" : 78,
"fitness" : 140
},
{
"num_generacio" : 79,
"fitness" : 131.75
},
{
"num_generacio" : 80,
"fitness" : 130.75
},
{
"num_generacio" : 81,
"fitness" : 192.25
},
{
"num_generacio" : 82,
"fitness" : 187.25
},
{
"num_generacio" : 83,
"fitness" : 132
},
{
"num_generacio" : 84,
"fitness" : 149
},
{
"num_generacio" : 85,
"fitness" : 145
},
{
"num_generacio" : 86,
"fitness" : 133.25
},
{
"num_generacio" : 87,
"fitness" : 170
},
{
"num_generacio" : 88,
"fitness" : 131
},
{
"num_generacio" : 89,
"fitness" : 199
},
{
"num_generacio" : 90,
"fitness" : 175.25
},
{
"num_generacio" : 91,
"fitness" : 140.5
},
{
"num_generacio" : 92,
"fitness" : 196
},
{
"num_generacio" : 93,
"fitness" : 189
},
{
"num_generacio" : 94,
"fitness" : 145.5
},
{
"num_generacio" : 95,
"fitness" : 191.25
},
{
"num_generacio" : 96,
"fitness" : 161.25
},
{
"num_generacio" : 97,
"fitness" : 132
},
{
"num_generacio" : 98,
"fitness" : 182
},
{
"num_generacio" : 99,
"fitness" : 189.25
},
{
"num_generacio" : 100,
"fitness" : 159.5
},
{
"num_generacio" : 101,
"fitness" : 159.5
},
{
"num_generacio" : 102,
"fitness" : 188.75
},
{
"num_generacio" : 103,
"fitness" : 132.25
},
{
"num_generacio" : 104,
"fitness" : 159.5
},
{
"num_generacio" : 105,
"fitness" : 191.75
},
{
"num_generacio" : 106,
"fitness" : 132.25
},
{
"num_generacio" : 107,
"fitness" : 190.75
},
{
"num_generacio" : 108,
"fitness" : 145
},
{
"num_generacio" : 109,
"fitness" : 134
},
{
"num_generacio" : 110,
"fitness" : 196.75
},
{
"num_generacio" : 111,
"fitness" : 188
},
{
"num_generacio" : 112,
"fitness" : 140
},
{
"num_generacio" : 113,
"fitness" : 183.25
},
{
"num_generacio" : 114,
"fitness" : 133.25
},
{
"num_generacio" : 115,
"fitness" : 191
},
{
"num_generacio" : 116,
"fitness" : 155.75
},
{
"num_generacio" : 117,
"fitness" : 133
},
{
"num_generacio" : 118,
"fitness" : 152.25
},
{
"num_generacio" : 119,
"fitness" : 150.5
},
{
"num_generacio" : 120,
"fitness" : 193.75
},
{
"num_generacio" : 121,
"fitness" : 197.25
},
{
"num_generacio" : 122,
"fitness" : 193.75
},
{
"num_generacio" : 123,
"fitness" : 151.25
},
{
"num_generacio" : 124,
"fitness" : 191.75
},
{
"num_generacio" : 125,
"fitness" : 150
}
],
"màxim_fitness" :199,
"millor_ocell" :
{
"neurones_input" : 3,
"neurones_amagades" :0,
"neuornes_output" :1,
"conexions" : [
{
"desde" :0,
"fins" :3,
"importancia" :0.76857364177704},
{
"desde" :1,
"fins" :3,
"importancia" :0.75038027763367},
{
"desde" :2,
"fins" :3,
"importancia" :-0.68469661474228}
]
}
},
{
"num_partida" :14,
"generacions" :
[
{
"num_generacio" : 1,
"fitness" : 123.75
},
{
"num_generacio" : 2,
"fitness" : 209
},
{
"num_generacio" : 3,
"fitness" : 216.15
},
{
"num_generacio" : 4,
"fitness" : 2359.3
},
{
"num_generacio" : 5,
"fitness" : 94839.3500000049
},
{
"num_generacio" : 6,
"fitness" : 9981.05
},
{
"num_generacio" : 7,
"fitness" : 165438.399999996
},
{
"num_generacio" : 8,
"fitness" : 164840.949999997
},
{
"num_generacio" : 9,
"fitness" : 165007.199999997
}
],
"màxim_fitness" :165438.399999996,
"millor_ocell" :
{
"neurones_input" : 3,
"neurones_amagades" :0,
"neuornes_output" :1,
"conexions" : [
{
"desde" :0,
"fins" :3,
"importancia" :0.75721228122711},
{
"desde" :1,
"fins" :3,
"importancia" :-0.75179940462112},
{
"desde" :2,
"fins" :3,
"importancia" :-0.14147055149078}
]
}
},
{
"num_partida" :15,
"generacions" :
[
{
"num_generacio" : 1,
"fitness" : 1078.15
},
{
"num_generacio" : 2,
"fitness" : 180
},
{
"num_generacio" : 3,
"fitness" : 212.35
},
{
"num_generacio" : 4,
"fitness" : 139
},
{
"num_generacio" : 5,
"fitness" : 131.25
},
{
"num_generacio" : 6,
"fitness" : 178.25
},
{
"num_generacio" : 7,
"fitness" : 197.5
},
{
"num_generacio" : 8,
"fitness" : 166
},
{
"num_generacio" : 9,
"fitness" : 142.75
},
{
"num_generacio" : 10,
"fitness" : 215.35
},
{
"num_generacio" : 11,
"fitness" : 131
},
{
"num_generacio" : 12,
"fitness" : 131.75
},
{
"num_generacio" : 13,
"fitness" : 170.5
},
{
"num_generacio" : 14,
"fitness" : 163.25
},
{
"num_generacio" : 15,
"fitness" : 159
},
{
"num_generacio" : 16,
"fitness" : 157.75
},
{
"num_generacio" : 17,
"fitness" : 131
},
{
"num_generacio" : 18,
"fitness" : 163
},
{
"num_generacio" : 19,
"fitness" : 215.3
},
{
"num_generacio" : 20,
"fitness" : 131.5
},
{
"num_generacio" : 21,
"fitness" : 215.25
},
{
"num_generacio" : 22,
"fitness" : 143.5
},
{
"num_generacio" : 23,
"fitness" : 149
},
{
"num_generacio" : 24,
"fitness" : 220.05
},
{
"num_generacio" : 25,
"fitness" : 201.75
},
{
"num_generacio" : 26,
"fitness" : 202
},
{
"num_generacio" : 27,
"fitness" : 137
},
{
"num_generacio" : 28,
"fitness" : 136.75
},
{
"num_generacio" : 29,
"fitness" : 154.5
},
{
"num_generacio" : 30,
"fitness" : 138.5
},
{
"num_generacio" : 31,
"fitness" : 216.25
},
{
"num_generacio" : 32,
"fitness" : 138.5
},
{
"num_generacio" : 33,
"fitness" : 155.25
},
{
"num_generacio" : 34,
"fitness" : 179.75
},
{
"num_generacio" : 35,
"fitness" : 205.75
},
{
"num_generacio" : 36,
"fitness" : 162.75
},
{
"num_generacio" : 37,
"fitness" : 139.5
},
{
"num_generacio" : 38,
"fitness" : 139.5
},
{
"num_generacio" : 39,
"fitness" : 176.75
},
{
"num_generacio" : 40,
"fitness" : 162.75
},
{
"num_generacio" : 41,
"fitness" : 132
},
{
"num_generacio" : 42,
"fitness" : 131
},
{
"num_generacio" : 43,
"fitness" : 131
},
{
"num_generacio" : 44,
"fitness" : 204.5
},
{
"num_generacio" : 45,
"fitness" : 179.25
},
{
"num_generacio" : 46,
"fitness" : 189
},
{
"num_generacio" : 47,
"fitness" : 158
},
{
"num_generacio" : 48,
"fitness" : 199.25
},
{
"num_generacio" : 49,
"fitness" : 133.75
},
{
"num_generacio" : 50,
"fitness" : 154.25
},
{
"num_generacio" : 51,
"fitness" : 206.25
},
{
"num_generacio" : 52,
"fitness" : 200
},
{
"num_generacio" : 53,
"fitness" : 131.25
},
{
"num_generacio" : 54,
"fitness" : 131.5
},
{
"num_generacio" : 55,
"fitness" : 162.75
},
{
"num_generacio" : 56,
"fitness" : 133
},
{
"num_generacio" : 57,
"fitness" : 137
},
{
"num_generacio" : 58,
"fitness" : 149.75
},
{
"num_generacio" : 59,
"fitness" : 221.25
},
{
"num_generacio" : 60,
"fitness" : 158
},
{
"num_generacio" : 61,
"fitness" : 131.25
},
{
"num_generacio" : 62,
"fitness" : 139.75
},
{
"num_generacio" : 63,
"fitness" : 149
},
{
"num_generacio" : 64,
"fitness" : 215.3
},
{
"num_generacio" : 65,
"fitness" : 158.5
},
{
"num_generacio" : 66,
"fitness" : 204.5
},
{
"num_generacio" : 67,
"fitness" : 176.25
},
{
"num_generacio" : 68,
"fitness" : 199.25
},
{
"num_generacio" : 69,
"fitness" : 216.5
},
{
"num_generacio" : 70,
"fitness" : 208
},
{
"num_generacio" : 71,
"fitness" : 157.25
},
{
"num_generacio" : 72,
"fitness" : 148.5
},
{
"num_generacio" : 73,
"fitness" : 210.75
},
{
"num_generacio" : 74,
"fitness" : 215.25
},
{
"num_generacio" : 75,
"fitness" : 139.5
},
{
"num_generacio" : 76,
"fitness" : 206
},
{
"num_generacio" : 77,
"fitness" : 163
},
{
"num_generacio" : 78,
"fitness" : 212.75
},
{
"num_generacio" : 79,
"fitness" : 148.5
},
{
"num_generacio" : 80,
"fitness" : 157.25
},
{
"num_generacio" : 81,
"fitness" : 201.75
},
{
"num_generacio" : 82,
"fitness" : 206.25
},
{
"num_generacio" : 83,
"fitness" : 157
},
{
"num_generacio" : 84,
"fitness" : 217.8
},
{
"num_generacio" : 85,
"fitness" : 150.25
},
{
"num_generacio" : 86,
"fitness" : 133.25
},
{
"num_generacio" : 87,
"fitness" : 204.5
},
{
"num_generacio" : 88,
"fitness" : 131.25
},
{
"num_generacio" : 89,
"fitness" : 132
},
{
"num_generacio" : 90,
"fitness" : 203
},
{
"num_generacio" : 91,
"fitness" : 135.5
},
{
"num_generacio" : 92,
"fitness" : 138.5
},
{
"num_generacio" : 93,
"fitness" : 160
},
{
"num_generacio" : 94,
"fitness" : 1157.45
},
{
"num_generacio" : 95,
"fitness" : 142.75
},
{
"num_generacio" : 96,
"fitness" : 179.5
},
{
"num_generacio" : 97,
"fitness" : 132.25
},
{
"num_generacio" : 98,
"fitness" : 132.5
},
{
"num_generacio" : 99,
"fitness" : 203
},
{
"num_generacio" : 100,
"fitness" : 148.5
},
{
"num_generacio" : 101,
"fitness" : 143.25
},
{
"num_generacio" : 102,
"fitness" : 131.75
},
{
"num_generacio" : 103,
"fitness" : 157.75
},
{
"num_generacio" : 104,
"fitness" : 203.5
},
{
"num_generacio" : 105,
"fitness" : 162.75
},
{
"num_generacio" : 106,
"fitness" : 142.25
},
{
"num_generacio" : 107,
"fitness" : 139
},
{
"num_generacio" : 108,
"fitness" : 185.75
},
{
"num_generacio" : 109,
"fitness" : 211.15
},
{
"num_generacio" : 110,
"fitness" : 132.25
},
{
"num_generacio" : 111,
"fitness" : 201.5
},
{
"num_generacio" : 112,
"fitness" : 132.25
},
{
"num_generacio" : 113,
"fitness" : 142.75
},
{
"num_generacio" : 114,
"fitness" : 131
},
{
"num_generacio" : 115,
"fitness" : 213.65
},
{
"num_generacio" : 116,
"fitness" : 209.75
},
{
"num_generacio" : 117,
"fitness" : 176.75
},
{
"num_generacio" : 118,
"fitness" : 217.75
},
{
"num_generacio" : 119,
"fitness" : 214
},
{
"num_generacio" : 120,
"fitness" : 151.25
},
{
"num_generacio" : 121,
"fitness" : 133.5
},
{
"num_generacio" : 122,
"fitness" : 151.5
},
{
"num_generacio" : 123,
"fitness" : 131.5
},
{
"num_generacio" : 124,
"fitness" : 210
},
{
"num_generacio" : 125,
"fitness" : 206.5
}
],
"màxim_fitness" :1157.45,
"millor_ocell" :
{
"neurones_input" : 3,
"neurones_amagades" :0,
"neuornes_output" :1,
"conexions" : [
{
"desde" :0,
"fins" :3,
"importancia" :0.96730041503906},
{
"desde" :1,
"fins" :3,
"importancia" :-0.21188247203827},
{
"desde" :2,
"fins" :3,
"importancia" :-0.62589144706726}
]
}
},
{
"num_partida" :16,
"generacions" :
[
{
"num_generacio" : 1,
"fitness" : 25.5
},
{
"num_generacio" : 2,
"fitness" : 25.5
},
{
"num_generacio" : 3,
"fitness" : 63.2499999999999
},
{
"num_generacio" : 4,
"fitness" : 61.2499999999999
},
{
"num_generacio" : 5,
"fitness" : 131.25
},
{
"num_generacio" : 6,
"fitness" : 98.6499999999999
},
{
"num_generacio" : 7,
"fitness" : 128.75
},
{
"num_generacio" : 8,
"fitness" : 124
},
{
"num_generacio" : 9,
"fitness" : 169.75
},
{
"num_generacio" : 10,
"fitness" : 162.75
},
{
"num_generacio" : 11,
"fitness" : 114.75
},
{
"num_generacio" : 12,
"fitness" : 120
},
{
"num_generacio" : 13,
"fitness" : 113
},
{
"num_generacio" : 14,
"fitness" : 114.5
},
{
"num_generacio" : 15,
"fitness" : 128.75
},
{
"num_generacio" : 16,
"fitness" : 117.75
},
{
"num_generacio" : 17,
"fitness" : 176
},
{
"num_generacio" : 18,
"fitness" : 126.75
},
{
"num_generacio" : 19,
"fitness" : 183
},
{
"num_generacio" : 20,
"fitness" : 130.5
},
{
"num_generacio" : 21,
"fitness" : 174.5
},
{
"num_generacio" : 22,
"fitness" : 132.75
},
{
"num_generacio" : 23,
"fitness" : 140.5
},
{
"num_generacio" : 24,
"fitness" : 127
},
{
"num_generacio" : 25,
"fitness" : 126
},
{
"num_generacio" : 26,
"fitness" : 177
},
{
"num_generacio" : 27,
"fitness" : 143
},
{
"num_generacio" : 28,
"fitness" : 151
},
{
"num_generacio" : 29,
"fitness" : 145.5
},
{
"num_generacio" : 30,
"fitness" : 174.75
},
{
"num_generacio" : 31,
"fitness" : 176
},
{
"num_generacio" : 32,
"fitness" : 147.5
},
{
"num_generacio" : 33,
"fitness" : 145
},
{
"num_generacio" : 34,
"fitness" : 186.5
},
{
"num_generacio" : 35,
"fitness" : 170.75
},
{
"num_generacio" : 36,
"fitness" : 182
},
{
"num_generacio" : 37,
"fitness" : 127.75
},
{
"num_generacio" : 38,
"fitness" : 178.25
},
{
"num_generacio" : 39,
"fitness" : 127
},
{
"num_generacio" : 40,
"fitness" : 180.5
},
{
"num_generacio" : 41,
"fitness" : 176
},
{
"num_generacio" : 42,
"fitness" : 126.25
},
{
"num_generacio" : 43,
"fitness" : 174.75
},
{
"num_generacio" : 44,
"fitness" : 150.75
},
{
"num_generacio" : 45,
"fitness" : 126
},
{
"num_generacio" : 46,
"fitness" : 182.75
},
{
"num_generacio" : 47,
"fitness" : 154
},
{
"num_generacio" : 48,
"fitness" : 133
},
{
"num_generacio" : 49,
"fitness" : 168
},
{
"num_generacio" : 50,
"fitness" : 134.75
},
{
"num_generacio" : 51,
"fitness" : 168
},
{
"num_generacio" : 52,
"fitness" : 178.75
},
{
"num_generacio" : 53,
"fitness" : 133.75
},
{
"num_generacio" : 54,
"fitness" : 168.2
},
{
"num_generacio" : 55,
"fitness" : 184
},
{
"num_generacio" : 56,
"fitness" : 142.5
},
{
"num_generacio" : 57,
"fitness" : 185.25
},
{
"num_generacio" : 58,
"fitness" : 158.75
},
{
"num_generacio" : 59,
"fitness" : 156
},
{
"num_generacio" : 60,
"fitness" : 133.75
},
{
"num_generacio" : 61,
"fitness" : 135.5
},
{
"num_generacio" : 62,
"fitness" : 168.25
},
{
"num_generacio" : 63,
"fitness" : 185.75
},
{
"num_generacio" : 64,
"fitness" : 150.25
},
{
"num_generacio" : 65,
"fitness" : 156.75
},
{
"num_generacio" : 66,
"fitness" : 133.25
},
{
"num_generacio" : 67,
"fitness" : 133.75
},
{
"num_generacio" : 68,
"fitness" : 135.25
},
{
"num_generacio" : 69,
"fitness" : 133
},
{
"num_generacio" : 70,
"fitness" : 140
},
{
"num_generacio" : 71,
"fitness" : 183.25
},
{
"num_generacio" : 72,
"fitness" : 133
},
{
"num_generacio" : 73,
"fitness" : 192.75
},
{
"num_generacio" : 74,
"fitness" : 153.5
},
{
"num_generacio" : 75,
"fitness" : 133.5
},
{
"num_generacio" : 76,
"fitness" : 168.75
},
{
"num_generacio" : 77,
"fitness" : 145.25
},
{
"num_generacio" : 78,
"fitness" : 135.25
},
{
"num_generacio" : 79,
"fitness" : 137.75
},
{
"num_generacio" : 80,
"fitness" : 155.75
},
{
"num_generacio" : 81,
"fitness" : 133.25
},
{
"num_generacio" : 82,
"fitness" : 150.5
},
{
"num_generacio" : 83,
"fitness" : 145.25
},
{
"num_generacio" : 84,
"fitness" : 179
},
{
"num_generacio" : 85,
"fitness" : 187
},
{
"num_generacio" : 86,
"fitness" : 140.25
},
{
"num_generacio" : 87,
"fitness" : 134
},
{
"num_generacio" : 88,
"fitness" : 178.25
},
{
"num_generacio" : 89,
"fitness" : 133.25
},
{
"num_generacio" : 90,
"fitness" : 188.75
},
{
"num_generacio" : 91,
"fitness" : 148
},
{
"num_generacio" : 92,
"fitness" : 153.25
},
{
"num_generacio" : 93,
"fitness" : 138
},
{
"num_generacio" : 94,
"fitness" : 143
},
{
"num_generacio" : 95,
"fitness" : 145.25
},
{
"num_generacio" : 96,
"fitness" : 185.25
},
{
"num_generacio" : 97,
"fitness" : 147.75
},
{
"num_generacio" : 98,
"fitness" : 178.25
},
{
"num_generacio" : 99,
"fitness" : 137.75
},
{
"num_generacio" : 100,
"fitness" : 132.75
},
{
"num_generacio" : 101,
"fitness" : 155.75
},
{
"num_generacio" : 102,
"fitness" : 132.5
},
{
"num_generacio" : 103,
"fitness" : 176.5
},
{
"num_generacio" : 104,
"fitness" : 185.55
},
{
"num_generacio" : 105,
"fitness" : 176.55
},
{
"num_generacio" : 106,
"fitness" : 180.95
},
{
"num_generacio" : 107,
"fitness" : 166.75
},
{
"num_generacio" : 108,
"fitness" : 140
},
{
"num_generacio" : 109,
"fitness" : 180.75
},
{
"num_generacio" : 110,
"fitness" : 183.5
},
{
"num_generacio" : 111,
"fitness" : 161.5
},
{
"num_generacio" : 112,
"fitness" : 159.5
},
{
"num_generacio" : 113,
"fitness" : 140.5
},
{
"num_generacio" : 114,
"fitness" : 150.5
},
{
"num_generacio" : 115,
"fitness" : 180.5
},
{
"num_generacio" : 116,
"fitness" : 138
},
{
"num_generacio" : 117,
"fitness" : 132
},
{
"num_generacio" : 118,
"fitness" : 132.75
},
{
"num_generacio" : 119,
"fitness" : 164.5
},
{
"num_generacio" : 120,
"fitness" : 154.25
},
{
"num_generacio" : 121,
"fitness" : 132.5
},
{
"num_generacio" : 122,
"fitness" : 159.25
},
{
"num_generacio" : 123,
"fitness" : 180.25
},
{
"num_generacio" : 124,
"fitness" : 185.55
},
{
"num_generacio" : 125,
"fitness" : 159.25
}
],
"màxim_fitness" :192.75,
"millor_ocell" :
{
"neurones_input" : 3,
"neurones_amagades" :0,
"neuornes_output" :1,
"conexions" : [
{
"desde" :0,
"fins" :3,
"importancia" :0.51585578918457},
{
"desde" :1,
"fins" :3,
"importancia" :0.69821035861969},
{
"desde" :2,
"fins" :3,
"importancia" :-0.54074013233185}
]
}
},
{
"num_partida" :17,
"generacions" :
[
{
"num_generacio" : 1,
"fitness" : 181.55
},
{
"num_generacio" : 2,
"fitness" : 204.65
},
{
"num_generacio" : 3,
"fitness" : 3412.90000000001
},
{
"num_generacio" : 4,
"fitness" : 7829.45000000003
},
{
"num_generacio" : 5,
"fitness" : 164408.199999997
},
{
"num_generacio" : 6,
"fitness" : 164793.449999997
},
{
"num_generacio" : 7,
"fitness" : 165008.649999997
}
],
"màxim_fitness" :165008.649999997,
"millor_ocell" :
{
"neurones_input" : 3,
"neurones_amagades" :0,
"neuornes_output" :1,
"conexions" : [
{
"desde" :0,
"fins" :3,
"importancia" :0.90190613269806},
{
"desde" :1,
"fins" :3,
"importancia" :-0.86310607194901},
{
"desde" :2,
"fins" :3,
"importancia" :-0.1865901350975}
]
}
},
{
"num_partida" :18,
"generacions" :
[
{
"num_generacio" : 1,
"fitness" : 64.2499999999999
},
{
"num_generacio" : 2,
"fitness" : 85.2499999999999
},
{
"num_generacio" : 3,
"fitness" : 69.9999999999999
},
{
"num_generacio" : 4,
"fitness" : 100.75
},
{
"num_generacio" : 5,
"fitness" : 117.75
},
{
"num_generacio" : 6,
"fitness" : 125
},
{
"num_generacio" : 7,
"fitness" : 150.25
},
{
"num_generacio" : 8,
"fitness" : 140.5
},
{
"num_generacio" : 9,
"fitness" : 176.5
},
{
"num_generacio" : 10,
"fitness" : 179.5
},
{
"num_generacio" : 11,
"fitness" : 183.25
},
{
"num_generacio" : 12,
"fitness" : 185.5
},
{
"num_generacio" : 13,
"fitness" : 184.5
},
{
"num_generacio" : 14,
"fitness" : 172.75
},
{
"num_generacio" : 15,
"fitness" : 131.25
},
{
"num_generacio" : 16,
"fitness" : 182
},
{
"num_generacio" : 17,
"fitness" : 131
},
{
"num_generacio" : 18,
"fitness" : 163.5
},
{
"num_generacio" : 19,
"fitness" : 183
},
{
"num_generacio" : 20,
"fitness" : 132
},
{
"num_generacio" : 21,
"fitness" : 184.75
},
{
"num_generacio" : 22,
"fitness" : 179.5
},
{
"num_generacio" : 23,
"fitness" : 180
},
{
"num_generacio" : 24,
"fitness" : 156
},
{
"num_generacio" : 25,
"fitness" : 150
},
{
"num_generacio" : 26,
"fitness" : 183.25
},
{
"num_generacio" : 27,
"fitness" : 158.75
},
{
"num_generacio" : 28,
"fitness" : 158.75
},
{
"num_generacio" : 29,
"fitness" : 183
},
{
"num_generacio" : 30,
"fitness" : 155
},
{
"num_generacio" : 31,
"fitness" : 132.25
},
{
"num_generacio" : 32,
"fitness" : 180.25
},
{
"num_generacio" : 33,
"fitness" : 132.25
},
{
"num_generacio" : 34,
"fitness" : 155.5
},
{
"num_generacio" : 35,
"fitness" : 187.5
},
{
"num_generacio" : 36,
"fitness" : 184.5
},
{
"num_generacio" : 37,
"fitness" : 159
},
{
"num_generacio" : 38,
"fitness" : 150.25
},
{
"num_generacio" : 39,
"fitness" : 153.5
},
{
"num_generacio" : 40,
"fitness" : 184.7
},
{
"num_generacio" : 41,
"fitness" : 182.25
},
{
"num_generacio" : 42,
"fitness" : 182.25
},
{
"num_generacio" : 43,
"fitness" : 160.75
},
{
"num_generacio" : 44,
"fitness" : 131.5
},
{
"num_generacio" : 45,
"fitness" : 162.25
},
{
"num_generacio" : 46,
"fitness" : 182.25
},
{
"num_generacio" : 47,
"fitness" : 153.5
},
{
"num_generacio" : 48,
"fitness" : 132.25
},
{
"num_generacio" : 49,
"fitness" : 188.25
},
{
"num_generacio" : 50,
"fitness" : 163.75
},
{
"num_generacio" : 51,
"fitness" : 140.5
},
{
"num_generacio" : 52,
"fitness" : 153.75
},
{
"num_generacio" : 53,
"fitness" : 178
},
{
"num_generacio" : 54,
"fitness" : 179.5
},
{
"num_generacio" : 55,
"fitness" : 150.5
},
{
"num_generacio" : 56,
"fitness" : 185.5
},
{
"num_generacio" : 57,
"fitness" : 179
},
{
"num_generacio" : 58,
"fitness" : 137.75
},
{
"num_generacio" : 59,
"fitness" : 175
},
{
"num_generacio" : 60,
"fitness" : 163.75
},
{
"num_generacio" : 61,
"fitness" : 140.5
},
{
"num_generacio" : 62,
"fitness" : 140.25
},
{
"num_generacio" : 63,
"fitness" : 135.5
},
{
"num_generacio" : 64,
"fitness" : 132.5
},
{
"num_generacio" : 65,
"fitness" : 155
},
{
"num_generacio" : 66,
"fitness" : 155
},
{
"num_generacio" : 67,
"fitness" : 131
},
{
"num_generacio" : 68,
"fitness" : 156
},
{
"num_generacio" : 69,
"fitness" : 183.25
},
{
"num_generacio" : 70,
"fitness" : 135
},
{
"num_generacio" : 71,
"fitness" : 140
},
{
"num_generacio" : 72,
"fitness" : 135
},
{
"num_generacio" : 73,
"fitness" : 178
},
{
"num_generacio" : 74,
"fitness" : 132.5
},
{
"num_generacio" : 75,
"fitness" : 131.25
},
{
"num_generacio" : 76,
"fitness" : 182.75
},
{
"num_generacio" : 77,
"fitness" : 160.75
},
{
"num_generacio" : 78,
"fitness" : 153.75
},
{
"num_generacio" : 79,
"fitness" : 182.5
},
{
"num_generacio" : 80,
"fitness" : 137.5
},
{
"num_generacio" : 81,
"fitness" : 183
},
{
"num_generacio" : 82,
"fitness" : 138
},
{
"num_generacio" : 83,
"fitness" : 137.75
},
{
"num_generacio" : 84,
"fitness" : 155
},
{
"num_generacio" : 85,
"fitness" : 150.5
},
{
"num_generacio" : 86,
"fitness" : 135.25
},
{
"num_generacio" : 87,
"fitness" : 183
},
{
"num_generacio" : 88,
"fitness" : 178.5
},
{
"num_generacio" : 89,
"fitness" : 150.25
},
{
"num_generacio" : 90,
"fitness" : 187
},
{
"num_generacio" : 91,
"fitness" : 156
},
{
"num_generacio" : 92,
"fitness" : 150.25
},
{
"num_generacio" : 93,
"fitness" : 155.75
},
{
"num_generacio" : 94,
"fitness" : 131.75
},
{
"num_generacio" : 95,
"fitness" : 140.25
},
{
"num_generacio" : 96,
"fitness" : 180.5
},
{
"num_generacio" : 97,
"fitness" : 135.25
},
{
"num_generacio" : 98,
"fitness" : 183.5
},
{
"num_generacio" : 99,
"fitness" : 177
},
{
"num_generacio" : 100,
"fitness" : 137.5
},
{
"num_generacio" : 101,
"fitness" : 132.5
},
{
"num_generacio" : 102,
"fitness" : 132.5
},
{
"num_generacio" : 103,
"fitness" : 177
},
{
"num_generacio" : 104,
"fitness" : 177.75
},
{
"num_generacio" : 105,
"fitness" : 150
},
{
"num_generacio" : 106,
"fitness" : 135.5
},
{
"num_generacio" : 107,
"fitness" : 163.5
},
{
"num_generacio" : 108,
"fitness" : 133
},
{
"num_generacio" : 109,
"fitness" : 177.25
},
{
"num_generacio" : 110,
"fitness" : 131.5
},
{
"num_generacio" : 111,
"fitness" : 182.5
},
{
"num_generacio" : 112,
"fitness" : 166.5
},
{
"num_generacio" : 113,
"fitness" : 184.75
},
{
"num_generacio" : 114,
"fitness" : 150.5
},
{
"num_generacio" : 115,
"fitness" : 177.75
},
{
"num_generacio" : 116,
"fitness" : 131
},
{
"num_generacio" : 117,
"fitness" : 131.5
},
{
"num_generacio" : 118,
"fitness" : 132.5
},
{
"num_generacio" : 119,
"fitness" : 177
},
{
"num_generacio" : 120,
"fitness" : 176
},
{
"num_generacio" : 121,
"fitness" : 175.5
},
{
"num_generacio" : 122,
"fitness" : 175.25
},
{
"num_generacio" : 123,
"fitness" : 145.25
},
{
"num_generacio" : 124,
"fitness" : 133
},
{
"num_generacio" : 125,
"fitness" : 177.25
}
],
"màxim_fitness" :188.25,
"millor_ocell" :
{
"neurones_input" : 3,
"neurones_amagades" :0,
"neuornes_output" :1,
"conexions" : [
{
"desde" :0,
"fins" :3,
"importancia" :0.60365736484528},
{
"desde" :1,
"fins" :3,
"importancia" :0.91742050647736},
{
"desde" :2,
"fins" :3,
"importancia" :-0.67840784788132}
]
}
},
{
"num_partida" :19,
"generacions" :
[
{
"num_generacio" : 1,
"fitness" : 25.5
},
{
"num_generacio" : 2,
"fitness" : 25.5
},
{
"num_generacio" : 3,
"fitness" : 25.5
},
{
"num_generacio" : 4,
"fitness" : 25.5
},
{
"num_generacio" : 5,
"fitness" : 25.5
},
{
"num_generacio" : 6,
"fitness" : 25.5
},
{
"num_generacio" : 7,
"fitness" : 25.5
},
{
"num_generacio" : 8,
"fitness" : 25.5
},
{
"num_generacio" : 9,
"fitness" : 2177.4
},
{
"num_generacio" : 10,
"fitness" : 1086.15
},
{
"num_generacio" : 11,
"fitness" : 1113.65
},
{
"num_generacio" : 12,
"fitness" : 1094.9
},
{
"num_generacio" : 13,
"fitness" : 1100.15
},
{
"num_generacio" : 14,
"fitness" : 27.0000000000001
},
{
"num_generacio" : 15,
"fitness" : 1291.9
},
{
"num_generacio" : 16,
"fitness" : 223.55
},
{
"num_generacio" : 17,
"fitness" : 148.5
},
{
"num_generacio" : 18,
"fitness" : 1299.9
},
{
"num_generacio" : 19,
"fitness" : 243.3
},
{
"num_generacio" : 20,
"fitness" : 3506.30000000001
},
{
"num_generacio" : 21,
"fitness" : 1305.65
},
{
"num_generacio" : 22,
"fitness" : 185.9
},
{
"num_generacio" : 23,
"fitness" : 193.95
},
{
"num_generacio" : 24,
"fitness" : 185.25
},
{
"num_generacio" : 25,
"fitness" : 183.85
},
{
"num_generacio" : 26,
"fitness" : 1206.15
},
{
"num_generacio" : 27,
"fitness" : 3422.10000000001
},
{
"num_generacio" : 28,
"fitness" : 164676.649999997
},
{
"num_generacio" : 29,
"fitness" : 164790.449999997
},
{
"num_generacio" : 30,
"fitness" : 164525.399999997
}
],
"màxim_fitness" :164790.449999997,
"millor_ocell" :
{
"neurones_input" : 3,
"neurones_amagades" :0,
"neuornes_output" :1,
"conexions" : [
{
"desde" :0,
"fins" :3,
"importancia" :0.90303766727448},
{
"desde" :1,
"fins" :3,
"importancia" :-0.85749900341034},
{
"desde" :2,
"fins" :3,
"importancia" :-0.2610188126564}
]
}
}
]
}
